audit_agent/__init__.py
audit_agent/cli.py
audit_agent/ai/__init__.py
audit_agent/ai/analyzer.py
audit_agent/ai/config.py
audit_agent/ai/providers.py
audit_agent/ai/remediation.py
audit_agent/audit/__init__.py
audit_agent/audit/engine.py
audit_agent/core/__init__.py
audit_agent/core/credentials.py
audit_agent/core/logging_config.py
audit_agent/core/objects.py
audit_agent/core/policy.py
audit_agent/core/rules.py
audit_agent/devices/__init__.py
audit_agent/devices/base.py
audit_agent/devices/linux_iptables.py
audit_agent/enforcement/__init__.py
audit_agent/enforcement/engine.py
audit_agent/enforcement/remediation.py
audit_agent-1.0.0.dist-info/licenses/LICENSE
audit_agent-1.0.0.dist-info/METADATA
audit_agent-1.0.0.dist-info/WHEEL
audit_agent-1.0.0.dist-info/entry_points.txt
audit_agent-1.0.0.dist-info/top_level.txt
audit_agent-1.0.0.dist-info/RECORD
