Metadata-Version: 2.4
Name: audit-agent
Version: 1.0.0
Summary: Linux iptables Policy Enforcer & Auditor
Author-email: Mohammad Abu-Khader <mohammad.abukhader@hotmail.com>
License: MIT
Project-URL: Homepage, https://github.com/xoity/AuditAgent
Project-URL: Repository, https://github.com/xoity/AuditAgent
Project-URL: Documentation, https://github.com/xoity/AuditAgent
Keywords: linux,iptables,firewall,audit,compliance,security,Automation
Classifier: Development Status :: 3 - Alpha
Classifier: Intended Audience :: System Administrators
Classifier: License :: OSI Approved :: MIT License
Classifier: Programming Language :: Python :: 3.9
Classifier: Programming Language :: Python :: 3.10
Classifier: Programming Language :: Python :: 3.11
Classifier: Programming Language :: Python :: 3.12
Classifier: Programming Language :: Python :: 3.13
Classifier: Topic :: System :: Networking
Classifier: Topic :: System :: Systems Administration
Classifier: Topic :: Security
Requires-Python: >=3.9
License-File: LICENSE
Requires-Dist: paramiko>=2.11.0
Requires-Dist: requests>=2.28.0
Requires-Dist: pydantic>=2.0.0
Requires-Dist: rich>=13.0.0
Requires-Dist: typer>=0.9.0
Requires-Dist: pyyaml>=6.0
Requires-Dist: jinja2>=3.1.0
Requires-Dist: cryptography>=41.0.0
Provides-Extra: ai
Requires-Dist: google-generativeai>=0.3.0; extra == "ai"
Provides-Extra: dev
Requires-Dist: pytest>=7.0.0; extra == "dev"
Requires-Dist: pytest-asyncio>=0.21.0; extra == "dev"
Requires-Dist: pytest-cov>=4.0.0; extra == "dev"
Requires-Dist: ruff>=0.1.0; extra == "dev"
Requires-Dist: mypy>=1.5.0; extra == "dev"
Provides-Extra: docs
Requires-Dist: sphinx>=7.0.0; extra == "docs"
Requires-Dist: sphinx-rtd-theme>=1.3.0; extra == "docs"
Dynamic: license-file
